{
    "framework": "pytorch",
    "task": "token-classification",
    "model": {
        "type": "mgeo",
        "language": "zh",
        "id2label": {
            "0": "B-BD",
            "1": "B-BL",
            "2": "B-BS",
            "3": "B-Brand",
            "4": "B-CategorySuffix",
            "5": "B-Desc",
            "6": "B-Entity",
            "7": "B-NumEng",
            "8": "B-PA",
            "9": "B-PB",
            "10": "B-PC",
            "11": "B-PD",
            "12": "B-PE",
            "13": "B-PF",
            "14": "B-PG",
            "15": "B-PH",
            "16": "B-PS",
            "17": "B-RD",
            "18": "B-SA",
            "19": "B-SS",
            "20": "B-UA",
            "21": "B-UB",
            "22": "B-UC",
            "23": "B-UD",
            "24": "B-UE",
            "25": "B-YA",
            "26": "B-Yewu",
            "27": "B-ZZ",
            "28": "I-BL",
            "29": "I-BS",
            "30": "I-Brand",
            "31": "I-CategorySuffix",
            "32": "I-Desc",
            "33": "I-Entity",
            "34": "I-NumEng",
            "35": "I-PA",
            "36": "I-PB",
            "37": "I-PC",
            "38": "I-PD",
            "39": "I-PE",
            "40": "I-PF",
            "41": "I-PG",
            "42": "I-PH",
            "43": "I-PS",
            "44": "I-RD",
            "45": "I-SA",
            "46": "I-SS",
            "47": "I-UA",
            "48": "I-UB",
            "49": "I-UC",
            "50": "I-UD",
            "51": "I-UE",
            "52": "I-YA",
            "53": "I-Yewu",
            "54": "I-ZZ"
        },
        "label2id": {
            "B-BD": 0,
            "B-BL": 1,
            "B-BS": 2,
            "B-Brand": 3,
            "B-CategorySuffix": 4,
            "B-Desc": 5,
            "B-Entity": 6,
            "B-NumEng": 7,
            "B-PA": 8,
            "B-PB": 9,
            "B-PC": 10,
            "B-PD": 11,
            "B-PE": 12,
            "B-PF": 13,
            "B-PG": 14,
            "B-PH": 15,
            "B-PS": 16,
            "B-RD": 17,
            "B-SA": 18,
            "B-SS": 19,
            "B-UA": 20,
            "B-UB": 21,
            "B-UC": 22,
            "B-UD": 23,
            "B-UE": 24,
            "B-YA": 25,
            "B-Yewu": 26,
            "B-ZZ": 27,
            "I-BL": 28,
            "I-BS": 29,
            "I-Brand": 30,
            "I-CategorySuffix": 31,
            "I-Desc": 32,
            "I-Entity": 33,
            "I-NumEng": 34,
            "I-PA": 35,
            "I-PB": 36,
            "I-PC": 37,
            "I-PD": 38,
            "I-PE": 39,
            "I-PF": 40,
            "I-PG": 41,
            "I-PH": 42,
            "I-PS": 43,
            "I-RD": 44,
            "I-SA": 45,
            "I-SS": 46,
            "I-UA": 47,
            "I-UB": 48,
            "I-UC": 49,
            "I-UD": 50,
            "I-UE": 51,
            "I-YA": 52,
            "I-Yewu": 53,
            "I-ZZ": 54
        },
        "num_labels": 55
    },
    "pipeline": {
        "type": "token-classification"
    },
    "preprocessor": {
        "type": "token-cls-tokenizer",
        "padding": "max_length",
        "model_dir": "mgeo_duiwai_v1",
        "label2id": {
            "B-BD": 0,
            "B-BL": 1,
            "B-BS": 2,
            "B-Brand": 3,
            "B-CategorySuffix": 4,
            "B-Desc": 5,
            "B-Entity": 6,
            "B-NumEng": 7,
            "B-PA": 8,
            "B-PB": 9,
            "B-PC": 10,
            "B-PD": 11,
            "B-PE": 12,
            "B-PF": 13,
            "B-PG": 14,
            "B-PH": 15,
            "B-PS": 16,
            "B-RD": 17,
            "B-SA": 18,
            "B-SS": 19,
            "B-UA": 20,
            "B-UB": 21,
            "B-UC": 22,
            "B-UD": 23,
            "B-UE": 24,
            "B-YA": 25,
            "B-Yewu": 26,
            "B-ZZ": 27,
            "I-BL": 28,
            "I-BS": 29,
            "I-Brand": 30,
            "I-CategorySuffix": 31,
            "I-Desc": 32,
            "I-Entity": 33,
            "I-NumEng": 34,
            "I-PA": 35,
            "I-PB": 36,
            "I-PC": 37,
            "I-PD": 38,
            "I-PE": 39,
            "I-PF": 40,
            "I-PG": 41,
            "I-PH": 42,
            "I-PS": 43,
            "I-RD": 44,
            "I-SA": 45,
            "I-SS": 46,
            "I-UA": 47,
            "I-UB": 48,
            "I-UC": 49,
            "I-UD": 50,
            "I-UE": 51,
            "I-YA": 52,
            "I-Yewu": 53,
            "I-ZZ": 54
        },
        "first_sequence": "tokens",
        "label": "ner_tags",
        "mode": "inference",
        "use_fast": true
    },
    "train": {
        "work_dir": "/tmp",
        "max_epochs": 10,
        "dataloader": {
            "batch_size_per_gpu": 100,
            "workers_per_gpu": 1
        },
        "optimizer": {
            "type": "AdamW",
            "lr": 5e-05
        },
        "lr_scheduler": {
            "type": "LinearLR",
            "start_factor": 1.0,
            "end_factor": 0.0,
            "total_iters": 15550
        },
        "hooks": [
            {
                "type": "CheckpointHook",
                "interval": 1
            },
            {
                "type": "TextLoggerHook",
                "interval": 100
            },
            {
                "type": "IterTimerHook"
            },
            {
                "type": "EvaluationHook",
                "by_epoch": true
            }
        ]
    },
    "evaluation": {
        "dataloader": {
            "batch_size_per_gpu": 100,
            "workers_per_gpu": 1,
            "shuffle": false
        }
    },
    "dataset": {
        "train": {
            "labels": [
                "B-BD",
                "B-BL",
                "B-BS",
                "B-Brand",
                "B-CategorySuffix",
                "B-Desc",
                "B-Entity",
                "B-NumEng",
                "B-PA",
                "B-PB",
                "B-PC",
                "B-PD",
                "B-PE",
                "B-PF",
                "B-PG",
                "B-PH",
                "B-PS",
                "B-RD",
                "B-SA",
                "B-SS",
                "B-UA",
                "B-UB",
                "B-UC",
                "B-UD",
                "B-UE",
                "B-YA",
                "B-Yewu",
                "B-ZZ",
                "I-BL",
                "I-BS",
                "I-Brand",
                "I-CategorySuffix",
                "I-Desc",
                "I-Entity",
                "I-NumEng",
                "I-PA",
                "I-PB",
                "I-PC",
                "I-PD",
                "I-PE",
                "I-PF",
                "I-PG",
                "I-PH",
                "I-PS",
                "I-RD",
                "I-SA",
                "I-SS",
                "I-UA",
                "I-UB",
                "I-UC",
                "I-UD",
                "I-UE",
                "I-YA",
                "I-Yewu",
                "I-ZZ"
            ],
            "first_sequence": "tokens",
            "label": "ner_tags",
            "sequence_length": 128,
            "mode": "train"
        }
    },
    "allow_remote": true
}